ramble/__init__.py
ramble/ramble.py
ramble/ramble_config.py
ramble/ramble_contents.py
ramble/ramble_engine.py
ramble/settings.yml
ramble/utils.py
ramble/controls/__init__.py
ramble/controls/dbus.py
ramble/controls/stdin.py
ramble/lib/__init__.py
ramble/lib/ramble_screen.py
ramble/middlewares/__init__.py
ramble/middlewares/moodbase.py
ramble/middlewares/publicbase.py
ramble/middlewares/taboo.py
ramble/players/__init__.py
ramble/players/chromecast.py
ramble/players/chromium.py
ramble/players/dummy.py
ramble/players/mpd.py
ramble/players/mpv.py
ramble/players/nats.py
ramble/players/offline.py
ramble/players/pictures.py
ramble/players/stan.py
ramble/protocols/__init__.py
ramble/protocols/rss.py
ramble/protocols/sublink.py
ramble/protocols/youtube.py
ramble/sources/__init__.py
ramble/sources/api.py
ramble/sources/bookmarks.py
ramble/sources/dummy1.py
ramble/sources/dummy2.py
ramble/sources/file.py
ramble/sources/mongo.py
ramble/sources/notifications.py
ramble/sources/offline.py
ramble/sources/stan.py
ramble/sources/taboo.py
ramble-0.0.5.dist-info/LICENSE.txt
ramble-0.0.5.dist-info/LICENSE~
ramble-0.0.5.dist-info/METADATA
ramble-0.0.5.dist-info/WHEEL
ramble-0.0.5.dist-info/entry_points.txt
ramble-0.0.5.dist-info/top_level.txt
ramble-0.0.5.dist-info/RECORD
