Metadata-Version: 2.1
Name: ramble
Version: 0.0.5
Summary: A program for playing  content automatically according to time, location and place
Home-page: UNKNOWN
Author: UNKNOWN
Author-email: UNKNOWN
License: BSD
Platform: UNKNOWN
Classifier: Natural Language :: English
Classifier: License :: OSI Approved :: BSD License
Classifier: Programming Language :: Python
Classifier: Programming Language :: Python :: 3.7
Requires-Dist: aiohttp
Requires-Dist: async-lru
Requires-Dist: cproto
Requires-Dist: python-mpd2
Requires-Dist: coloredlogs
Requires-Dist: diskcache
Requires-Dist: dynaconf
Requires-Dist: clize
Requires-Dist: catt
Requires-Dist: quart
Requires-Dist: feedparser
Requires-Dist: setuptools
Requires-Dist: pyglet
Requires-Dist: dbussy
Requires-Dist: PyYAML
Requires-Dist: BeautifulSoup4
